odoo/addons/message_connector_base/README.rst
odoo/addons/message_connector_base/__init__.py
odoo/addons/message_connector_base/__manifest__.py
odoo/addons/message_connector_base/data/actions_server.xml
odoo/addons/message_connector_base/data/message_connector_base_queue_job.xml
odoo/addons/message_connector_base/i18n/es.po
odoo/addons/message_connector_base/models/__init__.py
odoo/addons/message_connector_base/models/base_automation.py
odoo/addons/message_connector_base/models/ir_actions.py
odoo/addons/message_connector_base/models/message_connector_channel.py
odoo/addons/message_connector_base/models/message_connector_connection.py
odoo/addons/message_connector_base/models/message_connector_field_builder.py
odoo/addons/message_connector_base/models/message_connector_message_builder.py
odoo/addons/message_connector_base/models/queue_job.py
odoo/addons/message_connector_base/models/res_company.py
odoo/addons/message_connector_base/models/res_config_settings.py
odoo/addons/message_connector_base/security/ir.model.access.csv
odoo/addons/message_connector_base/security/message_connector_base_security.xml
odoo/addons/message_connector_base/static/description/icon.png
odoo/addons/message_connector_base/static/src/img/icon.png
odoo/addons/message_connector_base/views/ir_actions_server_views.xml
odoo/addons/message_connector_base/views/message_connector_channel_views.xml
odoo/addons/message_connector_base/views/message_connector_connection_views.xml
odoo/addons/message_connector_base/views/message_connector_field_builder_views.xml
odoo/addons/message_connector_base/views/message_connector_message_builder_views.xml
odoo/addons/message_connector_base/views/res_config_settings_views.xml
odoo/addons/message_connector_base/wizard/__init__.py
odoo/addons/message_connector_base/wizard/wizard_send_test_message.py
odoo/addons/message_connector_base/wizard/wizard_send_test_message_views.xml
odoo/addons/message_connector_base/wizard/wizard_test_response.py
odoo_addon_message_connector_base-15.0.1.0.0.2.dist-info/METADATA
odoo_addon_message_connector_base-15.0.1.0.0.2.dist-info/WHEEL
odoo_addon_message_connector_base-15.0.1.0.0.2.dist-info/top_level.txt
odoo_addon_message_connector_base-15.0.1.0.0.2.dist-info/RECORD
