Metadata-Version: 2.1
Name: odoo-addon-message_connector_base
Version: 15.0.1.0.0.2
Requires-Python: >=3.8
Requires-Dist: odoo-addon-mass_editing>=15.0dev,<15.1dev
Requires-Dist: odoo-addon-queue_job>=15.0dev,<15.1dev
Requires-Dist: odoo>=15.0a,<15.1dev
Summary: Message Connector Base
Home-page: https://github.com/sygel-technology/sy-social
License: AGPL-3
Author: Sygel, Odoo Community Association (OCA)
Author-email: support@odoo-community.org
Classifier: Programming Language :: Python
Classifier: Framework :: Odoo
Classifier: Framework :: Odoo :: 15.0
Classifier: License :: OSI Approved :: GNU Affero General Public License v3
